<Properties StartupConfiguration="{34745B3E-B2F9-4E3C-AF45-C48F908C1AFF}|Default">
  <MonoDevelop.Ide.ItemProperties.ElephantsProject PreferredExecutionTarget="/Applications/Google Chrome.app" />
  <MonoDevelop.Ide.Workbench ActiveDocument="ElephantsProject/Elephants.json">
    <Files>
      <File FileName="ElephantsProject/ElephantService.cs" Line="17" Column="1" />
      <File FileName="ElephantsProject/Elephant.cs" Line="29" Column="6" />
      <File FileName="ElephantsProject/Elephants.json" Line="1" Column="1" />
      <File FileName="ElephantsProject/Controllers/ElephantController.cs" Line="84" Column="10" NotebookId="1" />
      <File FileName="ElephantsProjectTests/UnitTest1.cs" Line="18" Column="34" NotebookId="1" />
    </Files>
    <Pads>
      <Pad Id="ProjectPad">
        <State name="__root__">
          <Node name="ElephantsProject" expanded="True">
            <Node name="ElephantsProject" expanded="True">
              <Node name="Service" expanded="True" />
              <Node name="Elephants.json" selected="True" />
            </Node>
            <Node name="ElephantsProjectTests" expanded="True" />
          </Node>
        </State>
      </Pad>
      <Pad Id="MonoDevelop.Debugger.WatchPad">
        <State>
          <Value>elephant</Value>
        </State>
      </Pad>
    </Pads>
  </MonoDevelop.Ide.Workbench>
  <MonoDevelop.Ide.DebuggingService.PinnedWatches>
    <Watch file="../../../../../../CSharp/c-sharp-katas/Katas/KatasProject/Katas.cs" line="14" column="21" endLine="14" endColumn="24" offsetX="-1" offsetY="-1" expression="Katas.Models.Animal" liveUpdate="False" />
  </MonoDevelop.Ide.DebuggingService.PinnedWatches>
  <MonoDevelop.Ide.Workspace ActiveConfiguration="Debug" />
  <MonoDevelop.Ide.DebuggingService.Breakpoints>
    <BreakpointStore />
  </MonoDevelop.Ide.DebuggingService.Breakpoints>
  <MultiItemStartupConfigurations />
</Properties>